{"VTuber":{"id":"038ee6280ef742bcad8450ad52049944","activity":"active","name":"緋尹夜","imgUrl":"https://yt3.ggpht.com/6Q6_E9CF3Uj5YpeCzrF21_Yjsc9qHqmEVu0M0oz4ZKAb0Xuc9SLhBXaHn0xj8fLX1Md827Mowjs=s240-c-k-c0x00ffffff-no-rj","YouTube":{"subscriber":{"tag":"has","count":5480},"id":"UCAVh0Elx_7eImXZ2pBMhz6A"},"popularVideo":{"type":"YouTube","id":"ZE41cTLxqoA"},"group":"椛花夜露","nationality":"TW","livestreams":[{"title":"【Shadowverse: Worlds Beyond／闇影詩章凌越世界】哈魯兄弟公會發出一聲很酷的哼絕讚超生中！為了公會GEM，完全萌新來去天梯爬好爬滿！【緋尹夜Haruya】","videoUrl":"https://www.youtube.com/watch?v=HNRJGod1EKw","thumbnailUrl":"https://i.ytimg.com/vi/HNRJGod1EKw/mqdefault_live.jpg","startTime":"2025-06-23T03:52:31.0000000\u002B00:00"}]}}