{"VTuber":{"id":"0f2ad43c618943d19d5101f2d3c49ac9","activity":"active","name":"霍矢敋","imgUrl":"https://yt3.ggpht.com/yBImWwr2Q3DvjSN6yEVyxEtBNtGAcCk8OcsJ8B_UwJ8elqs5jNKcU_n8SAtsiGKTq5LHaeWtqA=s240-c-k-c0x00ffffff-no-rj","YouTube":{"subscriber":{"tag":"has","count":1200},"id":"UC9fN-5BAXljNjXmGbAyRZTQ"},"Twitch":{"follower":{"tag":"has","count":183},"id":"horskerch"},"popularVideo":{"type":"YouTube","id":"_REIc6ps8lY"},"nationality":"TW","debutDate":"2023-01-28","livestreams":[{"title":"【歌ってみた】Dec./Horsker ft.@yobobysound| Metal cover","videoUrl":"https://www.youtube.com/watch?v=PbRH-8ybWvI","thumbnailUrl":"https://i.ytimg.com/vi/PbRH-8ybWvI/mqdefault.jpg","startTime":"2024-12-24T04:12:00.0000000\u002B00:00"}]}}