{"VTuber":{"id":"1ac97b8deb08470dafc128557532dd52","activity":"active","name":"波可莉絲","imgUrl":"https://yt3.ggpht.com/oL29mpxtZpKoLKahwnQOgvWBPrr4J5jZxUbS5rJpthDtovRorGlUL9jz2-N4iGrneEZAlHAU5g=s240-c-k-c0x00ffffff-no-rj","YouTube":{"subscriber":{"tag":"has","count":14500},"id":"UCFrLaCTU9h-MTPaMSo-BDzQ"},"Twitch":{"follower":{"tag":"has","count":359},"id":"pokeris_vtb"},"popularVideo":{"type":"YouTube","id":"uHls3PawJ5s"},"nationality":"TW","debutDate":"2025-09-24","livestreams":[{"title":"\uD83C\uDFB2會員禮記錄\uD83C\uDFB2這應該是我此生唯一一次做肉鬆的機會...｜波可莉絲 Pokeris","videoUrl":"https://www.youtube.com/watch?v=j5lkF-c5tCo","thumbnailUrl":"https://i.ytimg.com/vi/j5lkF-c5tCo/mqdefault_live.jpg","startTime":"2026-03-04T14:00:00.0000000\u002B00:00"}]}}