{"VTuber":{"id":"22a83c82e1914eb68b12e76b4ccb277c","activity":"active","name":"雪江央可","imgUrl":"https://yt3.ggpht.com/uPmJXh3GqSSatM_tXn62xxz1xLByCNvAudAdWtpvNkFg_vf1FEBlSDbBNWMqcKXLIt9yYZQFog=s240-c-k-c0x00ffffff-no-rj","YouTube":{"subscriber":{"tag":"has","count":362},"id":"UCLUIsnZHVQRtBi99SxMeAsQ"},"popularVideo":{"type":"YouTube","id":"iTTVo6-mF4o"},"group":"凜冬白晝","nationality":"TW","debutDate":"2024-06-08","livestreams":[{"title":"【萬惡的壺男】繼續往上爬︱雪江央可","videoUrl":"https://www.youtube.com/watch?v=31RgSOevVvQ","thumbnailUrl":"https://i.ytimg.com/vi/31RgSOevVvQ/mqdefault_live.jpg","startTime":"2024-08-16T12:30:00.0000000\u002B00:00"}]}}