{"VTuber":{"id":"27f5926236d04e34a08fdb7ab83940bc","activity":"active","name":"艾爾莉絲","imgUrl":"https://yt3.ggpht.com/qA3GrB03J01b3FFmLM9vtU8X09XiirncMa1ONSPuwbjLi6QxFv-lUkqyeXtGfuXUXU6M6GEFEQ=s240-c-k-c0x00ffffff-no-rj","YouTube":{"subscriber":{"tag":"has","count":1950},"id":"UCZD47M2JPm0G4LLvgxs2YmA"},"popularVideo":{"type":"YouTube","id":"UzTCnGsyN68"},"group":"兔窩","nationality":"UNKNOWN","debutDate":"2023-10-01","livestreams":[{"title":"雜談｜雖然時間有點晚但還沒有遲到 .ᐟ.ᐟ｜Eirlys","videoUrl":"https://www.youtube.com/watch?v=1-e7EK9Fvs8","thumbnailUrl":"https://i.ytimg.com/vi/1-e7EK9Fvs8/mqdefault_live.jpg","startTime":"2026-02-14T15:00:00.0000000\u002B00:00"}]}}