{"VTuber":{"id":"2c42a2d77b4c481bae57dc00a66c2f16","activity":"active","name":"真黑makuro","imgUrl":"https://yt3.ggpht.com/sFJULWxXxJ6gpME7Kg968-hUXXwGbKk5SEvWjs6e_DzUMVrK4Bw32todNASohT1A7roKEiknmg=s240-c-k-c0x00ffffff-no-rj","YouTube":{"subscriber":{"tag":"has","count":4870},"id":"UCNqQfIrZMLNNJNLB0AOnfAg"},"popularVideo":{"type":"YouTube","id":"-SlaAQvcd00"},"nationality":"HK","debutDate":"2021-05-23","livestreams":[{"title":"【寶可夢傳說Z-A】Acup【真黑/香港VTuber】","videoUrl":"https://www.youtube.com/watch?v=V3EL-wfD7xg","thumbnailUrl":"https://i.ytimg.com/vi/V3EL-wfD7xg/mqdefault_live.jpg","startTime":"2025-12-04T11:06:04.0000000\u002B00:00"}]}}