{"VTuber":{"id":"2d3deb7610dd4329ba77597dfdd13043","activity":"active","name":"玉子將軍","imgUrl":"https://static-cdn.jtvnw.net/jtv_user_pictures/c60ec946-c250-496e-98bf-0af5c01b7f7e-profile_image-300x300.png","YouTube":{"subscriber":{"tag":"has","count":46},"id":"UC-vYhb78Njbhcqm5u1XPXYA"},"Twitch":{"follower":{"tag":"has","count":1519},"id":"siumobbb"},"popularVideo":{"type":"Twitch","id":"2180402680"},"nationality":"HK","livestreams":[{"title":"【玉子】熱死 (๑´ㅂ\u0060๑) 2.0準備中~!dc !歐付寶","videoUrl":"https://www.twitch.tv/siumobbb","thumbnailUrl":"https://static-cdn.jtvnw.net/previews-ttv/live_user_siumobbb-178x100.jpg","startTime":"2024-07-08T12:42:20.0000000\u002B00:00"}]}}