{"VTuber":{"id":"3681a0b4e4bd48888473b1884f6ee420","activity":"active","name":"佐藍","imgUrl":"https://yt3.ggpht.com/zkcE8-PHZtY_65bMU5rWqlpZKK5qq6yXMb31ErTkFd3PV5FQ36rACOyn37_d3tJWbdZHzgWLQg=s240-c-k-c0x00ffffff-no-rj","YouTube":{"subscriber":{"tag":"has","count":36400},"id":"UCRvxgWZV-LYr0sPP0nmpTBw"},"popularVideo":{"type":"YouTube","id":"O1b2YTrJPug"},"group":"比鄰星域","nationality":"TW","debutDate":"2022-05-16","livestreams":[{"title":"【Vtuber大師】現役Vtuber來當營運！請叫我佐藤B，我一定要讓公司賺大錢\uD83D\uDE21","videoUrl":"https://www.youtube.com/watch?v=k5A5sgrYj9E","thumbnailUrl":"https://i.ytimg.com/vi/k5A5sgrYj9E/mqdefault_live.jpg","startTime":"2024-05-03T12:02:41.0000000\u002B00:00"},{"title":"我擅長的配音：狗 #vtuber中文 #vtuber精華 #佐藍 #搞笑 #anime #遊戲","videoUrl":"https://www.youtube.com/watch?v=1rHfk7cOwD4","thumbnailUrl":"https://i.ytimg.com/vi/1rHfk7cOwD4/mqdefault.jpg","startTime":"2024-05-04T11:00:00.0000000\u002B00:00"}]}}