{"VTuber":{"id":"3dda133703f64b019d7eea0c5cb55335","activity":"active","name":"瀰婭","imgUrl":"https://yt3.ggpht.com/xzz5_GC3uQNmrM2h4gspj5bwLwKUvK1twN5n5XAFmtgGVUdlqfJ1DK75djCUifPLQPup2myZZ6A=s240-c-k-c0x00ffffff-no-rj","YouTube":{"subscriber":{"tag":"has","count":20600},"id":"UCIR0USMXU0r7N8spBJHNA7A"},"Twitch":{"follower":{"tag":"has","count":19570},"id":"miamya0615"},"popularVideo":{"type":"Twitch","id":"2219699057"},"nationality":"TW","livestreams":[{"title":"【瀰婭ミア】9/6(五)午後雷陣雨的季節","videoUrl":"https://www.twitch.tv/miamya0615","thumbnailUrl":"https://static-cdn.jtvnw.net/previews-ttv/live_user_miamya0615-178x100.jpg","startTime":"2024-09-06T08:00:58.0000000\u002B00:00"}]}}