{"VTuber":{"id":"4071b27c63424e1f9882ebe04a884586","activity":"active","name":"若白ルオバイ","imgUrl":"https://static-cdn.jtvnw.net/jtv_user_pictures/23aed98d-636d-4cd6-ac64-12b04cb30859-profile_image-300x300.png","YouTube":{"subscriber":{"tag":"has","count":296},"id":"UCySgTNcqMtMcPn6V2WPKW1A"},"Twitch":{"follower":{"tag":"has","count":3040},"id":"snowwolf0627"},"popularVideo":{"type":"Twitch","id":"2466999196"},"nationality":"UNKNOWN","debutDate":"2024-12-27","livestreams":[{"title":"✧˖06/02 生日月.✧第4隻| !生日 | @snowwolf0627","videoUrl":"https://www.twitch.tv/snowwolf0627","thumbnailUrl":"https://static-cdn.jtvnw.net/previews-ttv/live_user_snowwolf0627-178x100.jpg","startTime":"2025-06-01T18:28:50.0000000\u002B00:00"},{"title":"✧06/02 生日月✧ 老婆修練之旅day.2","videoUrl":"https://www.youtube.com/watch?v=1F0pbhNZtBE","thumbnailUrl":"https://i.ytimg.com/vi/1F0pbhNZtBE/mqdefault_live.jpg","startTime":"2025-06-02T11:13:09.0000000\u002B00:00"}]}}