{"VTuber":{"id":"40bb881e52be4d8b9c66a60be89e0504","activity":"active","name":"銀禰","imgUrl":"https://yt3.ggpht.com/OOszkP5Zm7l3jAjMA_tfG2SmsymyLs1ZyoLzxNI0ZfoYgGiQUkGP8qIhfA8On1IUSqTBV0t9=s240-c-k-c0x00ffffff-no-rj","YouTube":{"subscriber":{"tag":"has","count":481},"id":"UCZOxb-d8nERhxBZRNIRnxgA"},"popularVideo":{"type":"YouTube","id":"jzvXObn3HZQ"},"nationality":"TW","debutDate":"2024-03-25","livestreams":[{"title":"【遊戲】只會玩亞連 ! 星爆上分之路【EP.9】｜傳說對決 觀眾場x排位｜ #傳說對決 #傳說 #台灣Vtuber  #vtuebr #男性Vtuber  #台V","videoUrl":"https://www.youtube.com/watch?v=-3i0I7iqBYI","thumbnailUrl":"https://i.ytimg.com/vi/-3i0I7iqBYI/mqdefault_live.jpg","startTime":"2024-11-11T09:05:39.0000000\u002B00:00"}]}}