{"VTuber":{"id":"4c127c01ba31487599018fc81ff1a3dd","activity":"active","name":"Meko","imgUrl":"https://yt3.ggpht.com/yj4vXYI-fUeQcqX80AEkGILK5e-RQslBu1o0NcGQzCJOUpdeAxCf5ac_mpcHOVqrELvb5HF6lxI=s240-c-k-c0x00ffffff-no-rj","YouTube":{"subscriber":{"tag":"has","count":566},"id":"UCfVrAUe2kU4QL6CD_0rr9jA"},"popularVideo":{"type":"YouTube","id":"Os4wQcV3sI8"},"nationality":"TW","livestreams":[{"title":"【Don\u0027t Starve Together】\uD83D\uDD34別挨餓連動！與新朋朋一起開心生存！我們鳩竟能不能活過一個季節呢? FT.@hitomiya0518 、 @lenyueh 、@seta9152","videoUrl":"https://www.youtube.com/watch?v=Ir6LbcB1J2E","thumbnailUrl":"https://i.ytimg.com/vi/Ir6LbcB1J2E/mqdefault_live.jpg","startTime":"2024-12-21T11:00:56.0000000\u002B00:00"}]}}