{"VTuber":{"id":"4dd71b1079284bdb8ba90198317e524d","activity":"active","name":"Leliea 莉莉亞","imgUrl":"https://yt3.ggpht.com/wv1AwcZYOw7_7_lO1AuwCA5Mraor-iMkknZOUqjtiA618J9A1-nGXjAEMigogXcv9qjLqjLjug=s240-c-k-c0x00ffffff-no-rj","YouTube":{"subscriber":{"tag":"has","count":2720},"id":"UCjqodZNa-07fg9UhRfTRu-A"},"popularVideo":{"type":"YouTube","id":"XdwnFR6YfVg"},"nationality":"HK","debutDate":"2022-02-27","livestreams":[{"title":"【NS2 Splatoon Raiders 斯普拉遁塗擊隊】 首發日直播 遊戲全畫面劇情實況攻略 Walkthrough EP1","videoUrl":"https://www.youtube.com/watch?v=IUD4PZ1hi14","thumbnailUrl":"https://i.ytimg.com/vi/IUD4PZ1hi14/mqdefault_live.jpg","startTime":"2026-07-23T10:15:00.0000000\u002B00:00"},{"title":"【NS2 Splatoon Raiders 斯普拉遁塗擊隊】遊戲全畫面劇情實況攻略 Walkthrough EP2","videoUrl":"https://www.youtube.com/watch?v=D9Jt8Dttqng","thumbnailUrl":"https://i.ytimg.com/vi/D9Jt8Dttqng/mqdefault_live.jpg","startTime":"2026-07-24T10:15:00.0000000\u002B00:00"},{"title":"【NS2 Splatoon Raiders 斯普拉遁塗擊隊】 遊戲全畫面劇情實況攻略 Walkthrough EP3","videoUrl":"https://www.youtube.com/watch?v=s5gJKNeTt8A","thumbnailUrl":"https://i.ytimg.com/vi/s5gJKNeTt8A/mqdefault_live.jpg","startTime":"2026-07-25T02:30:00.0000000\u002B00:00"}]}}