{"VTuber":{"id":"4f917f1ccdd74d34a3746c379282b6fe","activity":"active","name":"史黛菈·阿緹米斯","imgUrl":"https://yt3.ggpht.com/Wudn9rA8RUcrVsIARSAprTshzOggf73VBonXVeZEnA_SgWAKMWwEIcy38JxBxEoS8HO2O9L0=s240-c-k-c0x00ffffff-no-rj","YouTube":{"subscriber":{"tag":"has","count":2860},"id":"UCMIRiUkKHdL9O0CSK4-PWcA"},"Twitch":{"follower":{"tag":"has","count":1864},"id":"stellartemis2"},"popularVideo":{"type":"YouTube","id":"DqKq3_uQbn8"},"nationality":"TW","debutDate":"2024-02-02","livestreams":[{"title":"【生日合唱切片】林俊傑 - 小酒窩 ┃春春一條蟲/星月兔阿緹米斯","videoUrl":"https://www.youtube.com/watch?v=jlcfAGzVSO8","thumbnailUrl":"https://i.ytimg.com/vi/jlcfAGzVSO8/mqdefault.jpg","startTime":"2025-12-26T04:30:00.0000000\u002B00:00"}]}}