{"VTuber":{"id":"53c811a3e7814de2b76dd4e0c241a9e5","activity":"active","name":"月台","imgUrl":"https://yt3.ggpht.com/aRUUOmAX5DoXdsjVC7gMv_qKdtEZQ0ddN1lC741mW4uitgCqUjEcbFKIpnUZqKBeX7uq2IXam4k=s240-c-k-c0x00ffffff-no-rj","YouTube":{"subscriber":{"tag":"has","count":1860},"id":"UCSmxnibr6eaclXIqeL7ixGw"},"Twitch":{"follower":{"tag":"has","count":208},"id":"yuetaii"},"popularVideo":{"type":"YouTube","id":"_PbWxfP9HF4"},"nationality":"TW","debutDate":"2023-06-29","livestreams":[{"title":"\uD83D\uDCE6【Unpacking】最不會整理房間ㄉ阿台來了\uD83D\uDC4A\uD83C\uDFFB【月台\uD83C\uDF19YueTai】","videoUrl":"https://www.youtube.com/watch?v=Tvp5Uf9gGvA","thumbnailUrl":"https://i.ytimg.com/vi/Tvp5Uf9gGvA/mqdefault_live.jpg","startTime":"2024-03-23T14:30:00.0000000\u002B00:00"},{"title":"⁉️【台灣迷因二選一】誰是台灣迷因ㄉ霸主呢【月台\uD83C\uDF19YueTai】","videoUrl":"https://www.youtube.com/watch?v=PsxyeLmSY-E","thumbnailUrl":"https://i.ytimg.com/vi/PsxyeLmSY-E/mqdefault_live.jpg","startTime":"2024-03-24T14:00:00.0000000\u002B00:00"},{"title":"☀️【#縱型配信 】早安月台！睏睏狗勾ㄘ早餐【月台\uD83C\uDF19YueTai】#shorts","videoUrl":"https://www.youtube.com/watch?v=EZA90URT61E","thumbnailUrl":"https://i.ytimg.com/vi/EZA90URT61E/mqdefault_live.jpg","startTime":"2024-03-25T02:00:00.0000000\u002B00:00"},{"title":"\uD83C\uDC04️【雀魂觀眾場】都來挑戰阿台\uD83D\uDC4A\uD83C\uDFFB【月台\uD83C\uDF19YueTai】","videoUrl":"https://www.youtube.com/watch?v=B4JghMX5b0o","thumbnailUrl":"https://i.ytimg.com/vi/B4JghMX5b0o/mqdefault_live.jpg","startTime":"2024-03-31T14:00:00.0000000\u002B00:00"}]}}