{"VTuber":{"id":"5ed5801d24c7412fa3fa65a82124aad0","activity":"active","name":"棲蒔","imgUrl":"https://yt3.ggpht.com/HyVh6sRT8Am9AVsu-ugv67W86diTyp7CyeTT39niWgtT69AA6SaeXBfSs3b-Zur14Nxu16W2ugU=s240-c-k-c0x00ffffff-no-rj","YouTube":{"subscriber":{"tag":"has","count":6070},"id":"UCGJ1vQ_oS-qpohNyoR4sw6w"},"Twitch":{"follower":{"tag":"has","count":1867},"id":"seventy_vtuber"},"popularVideo":{"type":"YouTube","id":"vi_4xuCR8r4"},"nationality":"TW","debutDate":"2025-08-11","livestreams":[{"title":"【午蒔歌雜】我會為你盛開在每個週末的下午♡ 【棲蒔】","videoUrl":"https://www.youtube.com/watch?v=BAVky8mgSKc","thumbnailUrl":"https://i.ytimg.com/vi/BAVky8mgSKc/mqdefault_live.jpg","startTime":"2026-02-15T05:00:00.0000000\u002B00:00"}]}}