{"VTuber":{"id":"626750f4e7a745619c171c44fb1efcc0","activity":"active","name":"小小雪","imgUrl":"https://yt3.ggpht.com/cVmFgGlv3eAMDmBf2sNCI3TBmx1ij3Km4RK3fopqoYW5fNTC2IfosTl1dsVPpxgQu9WBNKfSVA=s240-c-k-c0x00ffffff-no-rj","YouTube":{"subscriber":{"tag":"has","count":45900},"id":"UCQymE4njJ-t9oahwX9-iC8w"},"Twitch":{"follower":{"tag":"has","count":10098},"id":"hosinoyasetsu"},"popularVideo":{"type":"YouTube","id":"uiUp_43iN_s"},"nationality":"TW","debutDate":"2021-02-08","livestreams":[{"title":"【闇影詩章：凌越世界】土印巫師 日本職業玩家30連勝!全講解【天使Vtuber小雪Yukichan】#SkyboundDragons  #蒼空六龍","videoUrl":"https://www.youtube.com/watch?v=aBNR372fB5U","thumbnailUrl":"https://i.ytimg.com/vi/aBNR372fB5U/mqdefault.jpg","startTime":"2025-11-01T10:00:06.0000000\u002B00:00"},{"title":"【誕生日配信】今天我生日拆禮物啦!生日線下據售票開賣中 2025生日派對 2025 Birthday Party【天使Vtuber小雪Yukichan】#台灣Vtuber #Vtuber","videoUrl":"https://www.youtube.com/watch?v=DbVwU2MywIs","thumbnailUrl":"https://i.ytimg.com/vi/DbVwU2MywIs/mqdefault_live.jpg","startTime":"2025-11-02T10:00:00.0000000\u002B00:00"},{"title":"【オリジナル曲MV】遙久之風桜之舞【天使Vtuber小雪Yukichan】","videoUrl":"https://www.youtube.com/watch?v=eFDon-fjeTw","thumbnailUrl":"https://i.ytimg.com/vi/eFDon-fjeTw/mqdefault.jpg","startTime":"2025-11-02T10:00:00.0000000\u002B00:00"},{"title":"【凸待ち】2025生日凸待ち 社恐主播如果不事先邀約朋友會有人打來嗎!【天使Vtuber小雪Yukichan】#台灣Vtuber #Vtuber","videoUrl":"https://www.youtube.com/watch?v=Id67nUZlCns","thumbnailUrl":"https://i.ytimg.com/vi/Id67nUZlCns/mqdefault_live.jpg","startTime":"2025-11-03T10:00:00.0000000\u002B00:00"},{"title":"【凸待ち】生日月 跟騎士們徹夜暢聊 2025 Birthday Party with my Knight【天使Vtuber小雪Yukichan】#台灣Vtuber #Vtuber","videoUrl":"https://www.youtube.com/watch?v=p5MzlarhBVU","thumbnailUrl":"https://i.ytimg.com/vi/p5MzlarhBVU/mqdefault_live.jpg","startTime":"2025-11-04T10:00:00.0000000\u002B00:00"}]}}