{"VTuber":{"id":"644e669aa31443fe9a61a14e75ebd21e","activity":"active","name":"格林諾辰","imgUrl":"https://static-cdn.jtvnw.net/jtv_user_pictures/e2593967-6529-4f20-a8a9-4d20c8143105-profile_image-300x300.png","Twitch":{"follower":{"tag":"has","count":7605},"id":"nouchen_"},"popularVideo":{"type":"Twitch","id":"2564269923"},"nationality":"TW","livestreams":[{"title":"【格林諾辰】我們聊天彈琴  !簽到 │ @nouchen_ │09/18","videoUrl":"https://www.twitch.tv/nouchen_","thumbnailUrl":"https://static-cdn.jtvnw.net/previews-ttv/live_user_nouchen_-178x100.jpg","startTime":"2025-09-18T04:08:26.0000000\u002B00:00"}]}}