{"VTuber":{"id":"82e63a8d4ae14beab89e13b43b35fce3","activity":"active","name":"波奇卡德霍","imgUrl":"https://yt3.ggpht.com/A_RhHcLBeXlAJE1G9fsBJomJHUe-4LuHxvAA6UCrJzullTnMjsBEzabMJdS2uwfMhQTS7RbaCbI=s240-c-k-c0x00ffffff-no-rj","YouTube":{"subscriber":{"tag":"has","count":7360},"id":"UCjIciHMAc6Y-br3HU93AD1w"},"popularVideo":{"type":"YouTube","id":"FuMpCFW3Uro"},"group":"Mirolive","nationality":"TW","debutDate":"2023-08-12","livestreams":[{"title":"【雜談】睡不著就工作..工作到想睡/不開MIC工作台!跟我說早安","videoUrl":"https://www.youtube.com/watch?v=MKsbzqEj0uc","thumbnailUrl":"https://i.ytimg.com/vi/MKsbzqEj0uc/mqdefault_live.jpg","startTime":"2024-04-16T22:58:31.0000000\u002B00:00"}]}}