{"VTuber":{"id":"8c25e14dcc3a4f71895d58924c69dc0a","activity":"active","name":"小頡Jyeness","imgUrl":"https://yt3.ggpht.com/T72SYFOCqcPEFaX-C3xcULNLUVm3q8-Gclm5-UaUkVYXgt-9jKFbxdofRL6tn_-j3BbVIREt-qo=s240-c-k-c0x00ffffff-no-rj","YouTube":{"subscriber":{"tag":"has","count":3360},"id":"UCR3CHwRr63QzhHBBLQG54Mw"},"popularVideo":{"type":"YouTube","id":"2QZfFkCERTQ"},"nationality":"TW","debutDate":"2021-02-02","livestreams":[{"title":"【魔物獵人：荒野】開拓狩獵祭【小頡Jyeness】","videoUrl":"https://www.youtube.com/watch?v=ApDOviTD5OU","thumbnailUrl":"https://i.ytimg.com/vi/ApDOviTD5OU/mqdefault_live.jpg","startTime":"2025-03-30T11:26:10.0000000\u002B00:00"}]}}