{"VTuber":{"id":"8c3af9f56a3f4f1d84fcfcfa9f280c8d","activity":"active","name":"星間菖蒲＆紙野愛理","imgUrl":"https://yt3.ggpht.com/uo8Apz11sGE7a-5cYob-MNFevjAuVyR1DQ3fuPAnc3kYx8US1k2BvFy2_-AB0U0kK89dOhY_HTQ=s240-c-k-c0x00ffffff-no-rj","YouTube":{"subscriber":{"tag":"has","count":10800},"id":"UCzL1z9Mnr9Oba5ZjAqfa3lw"},"popularVideo":{"type":"YouTube","id":"U26xW5xcXG8"},"group":"小星人SmallAlien","nationality":"TW","debutDate":"2021-10-23","livestreams":[{"title":"【黑暗章魚燒預測大會】我作惡多端這麼久，終於還是在章魚燒餡料裡得到了報應！【*Seikan Iris 】","videoUrl":"https://www.youtube.com/watch?v=W9Y0HUDcxlA","thumbnailUrl":"https://i.ytimg.com/vi/W9Y0HUDcxlA/mqdefault_live.jpg","startTime":"2025-10-23T10:00:00.0000000\u002B00:00"},{"title":"【超心動！小菖的羞恥(地獄)操縱大會☆】可以這樣隨心所欲操縱主播的好機會不多了，一起羞恥play吧【*Seikan Iris 】","videoUrl":"https://www.youtube.com/watch?v=h3AwgDnGp1g","thumbnailUrl":"https://i.ytimg.com/vi/h3AwgDnGp1g/mqdefault_live.jpg","startTime":"2025-10-23T12:00:00.0000000\u002B00:00"},{"title":"【星間菖蒲四週年紀念直播】Happy 4th Anniversary☆時光匆匆飛逝，回頭看卻留下了滿天的星空和回憶【*Seikan Iris 】","videoUrl":"https://www.youtube.com/watch?v=gHSyGzDK85c","thumbnailUrl":"https://i.ytimg.com/vi/gHSyGzDK85c/mqdefault_live.jpg","startTime":"2025-10-23T13:30:00.0000000\u002B00:00"},{"title":"【空洞騎士：絲綢之歌#2】自己玩？不存在的！這次也靠好隊友NPC了！【Seikan Iris*】 feat.黑薔薇優璃愛","videoUrl":"https://www.youtube.com/watch?v=FXsXckav5Zs","thumbnailUrl":"https://i.ytimg.com/vi/FXsXckav5Zs/mqdefault_live.jpg","startTime":"2025-10-24T09:00:00.0000000\u002B00:00"}]}}