{"VTuber":{"id":"8f4142c5ead94656b4744b425d800fb8","activity":"active","name":"Justin Chuen","imgUrl":"https://yt3.ggpht.com/4yh0ZQkXLQMHA7nA_cjLK3Ox-aaMnoD7xvkhbCBMJrQmUpNsNayl94gN1oQpkrzZDtov9gCLkA=s240-c-k-c0x00ffffff-no-rj","YouTube":{"subscriber":{"tag":"has","count":549},"id":"UCPPtKhTOG99ClDAi6KJdFWQ"},"popularVideo":{"type":"YouTube","id":"PuvpHaq6mm4"},"nationality":"MY","livestreams":[{"title":"【プロセカ】排位賽直播","videoUrl":"https://www.youtube.com/watch?v=l9mov747TnI","thumbnailUrl":"https://i.ytimg.com/vi/l9mov747TnI/mqdefault_live.jpg","startTime":"2024-08-16T13:00:00.0000000\u002B00:00"}]}}