{"VTuber":{"id":"920d34819cf944e99cf469f7552d535f","activity":"active","name":"厭世醫師阿萬","imgUrl":"https://yt3.ggpht.com/9YkTgMpr33D38GCJHl97J7QfjmcnU_IJZOouyRltiLVXW2yL6i1aIrlm6PLf6RANVEuYSoMceQ=s240-c-k-c0x00ffffff-no-rj","YouTube":{"subscriber":{"tag":"has","count":15600},"id":"UCyEdVShpd0J11uf1Tsz-Udw"},"popularVideo":{"type":"YouTube","id":"cB-0BkzXGqo"},"nationality":"TW","debutDate":"2022-12-11","livestreams":[{"title":"【二週年特別企劃】β MAGIC！在值班室出現了意想不到的魔法 【厭世醫師阿萬】","videoUrl":"https://www.youtube.com/watch?v=ggP3xvIU2Hk","thumbnailUrl":"https://i.ytimg.com/vi/ggP3xvIU2Hk/mqdefault_live.jpg","startTime":"2024-12-14T12:06:51.0000000\u002B00:00"}]}}