{"VTuber":{"id":"abd64c9a64e04fb1b23faa2480c1c106","activity":"active","name":"魔哩煞","imgUrl":"https://yt3.ggpht.com/ECjpQb6CyC_wk-Txj1OeF_nCFvtOishyxuDEqBuAcQEGt0NvqyxT6EyKu61Gdiqfk3xVMcS1nQ=s240-c-k-c0x00ffffff-no-rj","YouTube":{"subscriber":{"tag":"has","count":221000},"id":"UCq5LQH-bD0Q3ZRhlclBAmqg"},"Twitch":{"follower":{"tag":"has","count":2279},"id":"fh_molissa"},"popularVideo":{"type":"YouTube","id":"8eAPiKZ8nNo"},"nationality":"TW","debutDate":"2022-05-10","livestreams":[{"title":"【周六驚魂日】玩恐怖遊戲怎麼會喘？San值管理失敗 ➡ 深蹲地獄啟動 \uD83D\uDD25","videoUrl":"https://www.youtube.com/watch?v=uxAm1FVJziI","thumbnailUrl":"https://i.ytimg.com/vi/uxAm1FVJziI/mqdefault_live.jpg","startTime":"2026-01-10T06:00:00.0000000\u002B00:00"},{"title":"【每周行程表】歡迎有禮貌的山雀組自由聊天\uD83D\uDC23","videoUrl":"https://www.youtube.com/watch?v=C7HnYLUt1BQ","thumbnailUrl":"https://i.ytimg.com/vi/C7HnYLUt1BQ/mqdefault_live.jpg","startTime":"2026-12-31T15:45:00.0000000\u002B00:00"}]}}