{"VTuber":{"id":"ad56a56e509c4b6fa0cf11ca959e3c72","activity":"active","name":"白音エルル","imgUrl":"https://yt3.ggpht.com/zpP9ijtO7p2m5JHjlmbuxEP9WqQL_GGuQb_nL4MrdM_jhebagFvENUTvyQdILMjVom2TRPr2=s240-c-k-c0x00ffffff-no-rj","YouTube":{"subscriber":{"tag":"has","count":7770},"id":"UC7M9zsObozmu0BBoDRIAkcQ"},"Twitch":{"follower":{"tag":"has","count":124},"id":"hakuneeruru"},"popularVideo":{"type":"YouTube","id":"APkMfOaTero"},"group":"終焉理想庭","nationality":"TW","debutDate":"2022-09-17","livestreams":[{"title":"【遊戲】我想成為影之強者！Master of Garden 手遊 看直播送免費虛寶序號【白音エルル/白音艾露露】#vtuber #遊戲實況 #エルルライブ #有露事故","videoUrl":"https://www.youtube.com/watch?v=pxIszSfHYXI","thumbnailUrl":"https://i.ytimg.com/vi/pxIszSfHYXI/mqdefault_live.jpg","startTime":"2024-08-22T13:00:00.0000000\u002B00:00"},{"title":"【雀魂】初見大歡迎！參加型 就算忙過頭也要打麻將!! 每周固定一天麻將台【白音エルル/白音艾露露】#雀魂  #日麻 #遊戲實況 #vtuber","videoUrl":"https://www.youtube.com/watch?v=NON3MLxJ1P8","thumbnailUrl":"https://i.ytimg.com/vi/NON3MLxJ1P8/mqdefault_live.jpg","startTime":"2024-08-23T12:00:00.0000000\u002B00:00"},{"title":"【企劃/現場直播】FF43 開拓動漫祭 每年兩次的祭典也見面吧 at 王國放送局 【白音エルル/白音艾露露】#FF43 #Vtuber","videoUrl":"https://www.youtube.com/watch?v=Nixu7qyaaAc","thumbnailUrl":"https://i.ytimg.com/vi/Nixu7qyaaAc/mqdefault_live.jpg","startTime":"2024-08-25T04:45:00.0000000\u002B00:00"}]}}