{"VTuber":{"id":"afe78c5051094e86bf9fdfe6cb2a4222","activity":"active","name":"ㄚ肚肚","imgUrl":"https://yt3.ggpht.com/ZZxmisCq643VL7N98W28i-LYQRRXzLMHTpRRAwSszl06wwdsDdfp-ut6-YQApAXpd1XthGp34A=s240-c-k-c0x00ffffff-no-rj","YouTube":{"subscriber":{"tag":"has","count":1120},"id":"UC2S7yERKgfE4WMkKizhXlIQ"},"popularVideo":{"type":"YouTube","id":"7jwt47y6g_U"},"nationality":"TW","debutDate":"2024-11-29","livestreams":[{"title":"來玩艾伊爾｜ㄚ肚肚Adudu #初見歡迎 #楓之谷M #maplestory","videoUrl":"https://www.youtube.com/watch?v=nIw1DPS8oEs","thumbnailUrl":"https://i.ytimg.com/vi/nIw1DPS8oEs/mqdefault_live.jpg","startTime":"2026-01-21T13:30:00.0000000\u002B00:00"}]}}