{"VTuber":{"id":"b0a7d70ae76549f5b4418e56ee4ad43f","activity":"active","name":"雲貓cloudcat","imgUrl":"https://static-cdn.jtvnw.net/jtv_user_pictures/f1e35736-5636-4bb7-b0a7-7479d0f9e8fd-profile_image-300x300.png","YouTube":{"subscriber":{"tag":"has","count":166},"id":"UCy6CfeEgqHO-nzN2X6GqQOg"},"Twitch":{"follower":{"tag":"has","count":406},"id":"cloudcat501"},"popularVideo":{"type":"Twitch","id":"2407932080"},"nationality":"TW","debutDate":"2025-03-14","livestreams":[{"title":"【連動】探索兩人的的抉擇之旅！共同合作，挑戰命運！【不同的冬天】ft.Bonpooa","videoUrl":"https://www.youtube.com/watch?v=Vdq1f5H5m1s","thumbnailUrl":"https://i.ytimg.com/vi/Vdq1f5H5m1s/mqdefault_live.jpg","startTime":"2025-03-28T02:00:00.0000000\u002B00:00"}]}}