{"VTuber":{"id":"bc7d14416ba24cc8819f0753e1f595f5","activity":"active","name":"FeroniaValens","imgUrl":"https://yt3.ggpht.com/loJpIxKnh5l7svX00LTcU-5d0WSSd6CMCi2atC0Jk0GphNJcaBeIfOOP87oyDCsoXXEBngGs_f4=s240-c-k-c0x00ffffff-no-rj","YouTube":{"subscriber":{"tag":"has","count":815},"id":"UCHNsQi7e56oSsO0fWMbkWuQ"},"popularVideo":{"type":"YouTube","id":"fKtUGsjPsrE"},"group":"Eticlas","nationality":"MY","debutDate":"2022-07-29","livestreams":[{"title":"【THE WITCH\u0027S HOUSE MV】 The witch in the forest 【Feronia Valens\uD83D\uDD8B️Eticlas】","videoUrl":"https://www.youtube.com/watch?v=XRIGWf-U1FA","thumbnailUrl":"https://i.ytimg.com/vi/XRIGWf-U1FA/mqdefault_live.jpg","startTime":"2024-09-22T12:30:00.0000000\u002B00:00"}]}}