{"VTuber":{"id":"c099b7e8d46c418d8e17097d496f3b83","activity":"active","name":"Ttspoon","imgUrl":"https://static-cdn.jtvnw.net/jtv_user_pictures/ba123c3c-0603-473d-a3ab-00c88eee1de1-profile_image-300x300.png","Twitch":{"follower":{"tag":"has","count":1855},"id":"ttspoon"},"popularVideo":{"type":"Twitch","id":"2283172394"},"nationality":"TW","livestreams":[{"title":"【踢踢】10.29 |  地獄列車  ₍ᐢ .ᆺ. ᐢ₎ 玩桌遊囉 | !幸運兔團  with 神秘力量 ✦看台15分鐘拿圖奇獎勵✦","videoUrl":"https://www.twitch.tv/ttspoon","thumbnailUrl":"https://static-cdn.jtvnw.net/previews-ttv/live_user_ttspoon-178x100.jpg","startTime":"2024-10-29T12:01:12.0000000\u002B00:00"}]}}