{"VTuber":{"id":"c0ce3bfbf1434af3a2a7bd7b2c38e7e7","activity":"active","name":"冬村Fuyumura","imgUrl":"https://yt3.ggpht.com/omwEf1s_bnaKOhFJskvVBEt8b4pz9Cv08QSVPbuBbvFzMe-HAR9j5ZQa_RBG7HYQ96F6mfcf748=s240-c-k-c0x00ffffff-no-rj","YouTube":{"subscriber":{"tag":"has","count":2170},"id":"UCEPeKtN_mRRia5m9RR-l-BQ"},"popularVideo":{"type":"YouTube","id":"wpQJFZoCFIk"},"nationality":"TW","debutDate":"2024-12-22","livestreams":[{"title":"【 Backrooms: Escape Together 】 冬村FM⛄ft. 姬乃\uD83D\uDC3E  藍玥\uD83C\uDF19  這個好像就是被稱作後室的地方，這裡是不是有怪物啊等一下   #初見歡迎   【遊戲】","videoUrl":"https://www.youtube.com/watch?v=ucCO6HmzHUM","thumbnailUrl":"https://i.ytimg.com/vi/ucCO6HmzHUM/mqdefault_live.jpg","startTime":"2026-07-18T11:33:23.0000000\u002B00:00"}]}}