{"VTuber":{"id":"c2777df3c8d341f4a1f0bb9cda8d9365","activity":"active","name":"柒夜","imgUrl":"https://static-cdn.jtvnw.net/jtv_user_pictures/bf12731b-cd83-4435-8df8-11f895a09e41-profile_image-300x300.png","Twitch":{"follower":{"tag":"has","count":1622},"id":"sevennightouo"},"popularVideo":{"type":"Twitch","id":"2520294087"},"group":"AsteriaLive","nationality":"TW","livestreams":[{"title":"0728 | 柒夜 @chi_ya_ouo  | chat | 小開一下就要去吃點東西","videoUrl":"https://www.twitch.tv/chi_ya_ouo","thumbnailUrl":"https://static-cdn.jtvnw.net/previews-ttv/live_user_chi_ya_ouo-178x100.jpg","startTime":"2025-07-28T10:47:03.0000000\u002B00:00"}]}}