{"VTuber":{"id":"c321746bebe740cb98625ca4cf6fb9a7","activity":"active","name":"иҺ“жһңиҠұеӨ•","imgUrl":"https://yt3.ggpht.com/PBV6UC4PZLXLJSFK1iKCuV-Huiox7h0bzOUfjY3tUlaSnEvsboup__TfiVJQEJWsRVsoEJXQkAc=s240-c-k-c0x00ffffff-no-rj","YouTube":{"subscriber":{"tag":"has","count":5030},"id":"UCPbEIlgqBQCWyZKrWrQwtUw"},"popularVideo":{"type":"YouTube","id":"EORcRlA_7eo"},"nationality":"TW","debutDate":"2022-02-14","livestreams":[{"title":"\uD83C\uDF53жҢ‘жҲ°50дәәжү“жӢӣе‘ј\uD83C\uDF53еҲқиҰӢеӨ§жӯЎиҝҺвңЁдҪ йЎҳж„ҸдҫҶи·ҹиҠұеӨ•жү“жӢӣе‘је—ҺвқӨпёҸгҖҗиҺ“жһңиҠұеӨ• berihanayu Ch.гҖ‘","videoUrl":"https://www.youtube.com/watch?v=mStF-xEDADI","thumbnailUrl":"https://i.ytimg.com/vi/mStF-xEDADI/mqdefault_live.jpg","startTime":"2024-10-26T10:31:53.0000000\u002B00:00"}]}}