{"VTuber":{"id":"c379e3f4f1eb41869ec465481b182e50","activity":"active","name":"姆莉醬","imgUrl":"https://yt3.ggpht.com/rn9ZkwoYuQ4R8eRG0Tko2gEdkru2m-79G1idjzrDW7M0QEvIEslS5yVfeM0RWAqQxRz4Z9Uj=s240-c-k-c0x00ffffff-no-rj","YouTube":{"subscriber":{"tag":"has","count":16600},"id":"UCsojcH8OTrg-imVpZzQ6MSw"},"popularVideo":{"type":"YouTube","id":"dWx7pryJmAg"},"group":"終焉理想庭","nationality":"TW","debutDate":"2024-08-02","livestreams":[{"title":"\uD83C\uDF207/20-7/26週星座運勢\uD83C\uDF20每週一中午星座台，本週暫時改週二！ #直播中 #Vtuber #12星座 #12星座運勢","videoUrl":"https://www.youtube.com/watch?v=fQCbm9gexuI","thumbnailUrl":"https://i.ytimg.com/vi/fQCbm9gexuI/mqdefault_live.jpg","startTime":"2026-07-21T04:00:33.0000000\u002B00:00"},{"title":"\uD83C\uDFA8遊戲連動：Meccha Chameleon\uD83C\uDFA8多人塗鴉躲貓貓！終焉理想庭之中誰最會躲呢？ #直播中 #mecchachameleon #めっちゃカメレオン #降落歡迎 #初見歡","videoUrl":"https://www.youtube.com/watch?v=K8o-VIL7h3o","thumbnailUrl":"https://i.ytimg.com/vi/K8o-VIL7h3o/mqdefault_live.jpg","startTime":"2026-07-21T13:00:32.0000000\u002B00:00"},{"title":"2026/7/13 - 2026/7/19 牡蠣國週表\uD83E\uDDAA","videoUrl":"https://www.youtube.com/watch?v=X2vU0umz568","thumbnailUrl":"https://i.ytimg.com/vi/X2vU0umz568/mqdefault_live.jpg","startTime":"2027-07-14T19:37:30.0000000\u002B00:00"}]}}