{"VTuber":{"id":"cd42e06c40534d9eac7e30a434e47d43","activity":"active","name":"帕豹","imgUrl":"https://yt3.ggpht.com/EGSoYsoHwgip2Bwt0EUCeN2x9r3RaoZzckuurXcDqAuuHgLrFv1UYzt-E0RgAB5ssRHlL4rf=s240-c-k-c0x00ffffff-no-rj","YouTube":{"subscriber":{"tag":"has","count":72000},"id":"UCltL6Tvv1aKrrYt4tnkmNtw"},"Twitch":{"follower":{"tag":"has","count":3299},"id":"pabovtb"},"popularVideo":{"type":"YouTube","id":"SCzXcOlMYtU"},"nationality":"TW","debutDate":"2021-08-07","livestreams":[{"title":"如果你也曾在深夜感到迷茫，希望這首歌能成為你的光。｜帕豹Pabo 【Official Music Video】 原創單曲《For the dream life》","videoUrl":"https://www.youtube.com/watch?v=W5lNneyPQfg","thumbnailUrl":"https://i.ytimg.com/vi/W5lNneyPQfg/mqdefault.jpg","startTime":"2026-03-22T12:00:00.0000000\u002B00:00"},{"title":"【生日新衣裝發表】這一次換我接住你!我會永遠在你身邊! ⟣  #帕豹Pabo","videoUrl":"https://www.youtube.com/watch?v=RhQwnPQP0AI","thumbnailUrl":"https://i.ytimg.com/vi/RhQwnPQP0AI/mqdefault_live.jpg","startTime":"2026-03-23T14:00:00.0000000\u002B00:00"}]}}