{"VTuber":{"id":"d2a7b2d142ea4076afcfc7263b9e09fd","activity":"active","name":"蕾雅Rhea Corey","imgUrl":"https://yt3.ggpht.com/y4s3h5Rtc3zoTFkpth-R_93SI8hAGfu14l9EDu6Ao5LL2c9DYE9-LJuxny5N1iUS0I28sep7Gg=s240-c-k-c0x00ffffff-no-rj","YouTube":{"subscriber":{"tag":"has","count":6890},"id":"UCjTHk7eBL8uacb2NJoygRLQ"},"Twitch":{"follower":{"tag":"has","count":773},"id":"rheacorey"},"popularVideo":{"type":"YouTube","id":"S_to1IqX2jY"},"nationality":"MY","livestreams":[{"title":"【聯動：PEAK】 如果我吐了你們可以背我上山嗎？ ft 伊諾/雷伊/愛夢 【蕾雅 馬來西亞Vtuber】","videoUrl":"https://www.youtube.com/watch?v=M0BCJ24U8yY","thumbnailUrl":"https://i.ytimg.com/vi/M0BCJ24U8yY/mqdefault_live.jpg","startTime":"2025-08-13T12:30:00.0000000\u002B00:00"},{"title":"【 #絢音彩歌 ~歌回接力~】 輪到我登場啦！我夏天的歌曲怎麽有點冷冷的！ 【蕾雅 馬來西亞Vtuber】","videoUrl":"https://www.youtube.com/watch?v=EKgiD6aUVFw","thumbnailUrl":"https://i.ytimg.com/vi/EKgiD6aUVFw/mqdefault_live.jpg","startTime":"2025-08-16T11:00:00.0000000\u002B00:00"}]}}