{"VTuber":{"id":"e63047f70b0b4a7eba70e7d8cbd507ec","activity":"active","name":"藤咲紫夜","imgUrl":"https://yt3.ggpht.com/Tp31on5Nru7HnANjS28Wh-EpUAvJrjewLSnsxi6uazgzTzfLG5gqi6d59XXTZyyabzHBCHmboA=s240-c-k-c0x00ffffff-no-rj","YouTube":{"subscriber":{"tag":"has","count":567},"id":"UC_EB4Ax3aVxIjtV4FMukm2Q"},"popularVideo":{"type":"YouTube","id":"1q2QAZKZhXQ"},"group":"Mugen Project Studio","nationality":"MY","debutDate":"2021-07-13","livestreams":[{"title":"【Esport Godfather/電競教父】新游戲試玩！電競賽場下的運籌帷幄「Shiya紫夜/ 马来西亚vtuber」","videoUrl":"https://www.youtube.com/watch?v=LwMrCAeLmr4","thumbnailUrl":"https://i.ytimg.com/vi/LwMrCAeLmr4/mqdefault_live.jpg","startTime":"2024-05-29T06:28:26.0000000\u002B00:00"}]}}