{"VTuber":{"id":"fad69c2a625446829ef410d9ef277c8f","activity":"active","name":"依涅斯","imgUrl":"https://yt3.ggpht.com/c0fX0dweIFQrNg2zKCFTtEYEFGe-sEQOvGZs_jq2HbdIxJnZ-QmWj4moQ-6efXExlRYjOmWIlA=s240-c-k-c0x00ffffff-no-rj","YouTube":{"subscriber":{"tag":"has","count":5010},"id":"UCkyjyDvMaZp8vcLTCpUzIAw"},"popularVideo":{"type":"YouTube","id":"y25aOoJxDIA"},"group":"塩月家","nationality":"TW","debutDate":"2024-02-24","livestreams":[{"title":"GamE︱來了~來了~ 來打了~\uD83D\uDD79️︱ 依涅斯Inez #初見さん大歓迎 #歡迎初見 #CS2 #CounterStrike2","videoUrl":"https://www.youtube.com/watch?v=U7tqfHoWYpw","thumbnailUrl":"https://i.ytimg.com/vi/U7tqfHoWYpw/mqdefault_live.jpg","startTime":"2026-07-22T12:00:02.0000000\u002B00:00"},{"title":"GamE︱瓦來瓦去~\uD83D\uDC40｜依涅斯Inez #初見さん大歓迎 #歡迎初見 #Valorant","videoUrl":"https://www.youtube.com/watch?v=uu9yRg9iC-0","thumbnailUrl":"https://i.ytimg.com/vi/uu9yRg9iC-0/mqdefault_live.jpg","startTime":"2026-07-24T12:00:00.0000000\u002B00:00"}]}}