{"VTuber":{"id":"fad69c2a625446829ef410d9ef277c8f","activity":"active","name":"依涅斯","imgUrl":"https://yt3.ggpht.com/ap2whAfgu9FxBplhfXJYJLMv0B49KE8IXlS0tuBbw_O9bs1qA0kVCYc9AbVSODRZmIuFt7mNLh4=s240-c-k-c0x00ffffff-no-rj","YouTube":{"subscriber":{"tag":"has","count":1480},"id":"UCkyjyDvMaZp8vcLTCpUzIAw"},"popularVideo":{"type":"YouTube","id":"PtclV8vd1p0"},"group":"塩月家","nationality":"TW","debutDate":"2024-02-24","livestreams":[{"title":"【Gaming】突發\uD83D\uDC9C今天來打麻將囉❣️ #初見さん大歓迎 #歡迎初見 #雀魂 #突發","videoUrl":"https://www.youtube.com/watch?v=PmCVZNqSTYw","thumbnailUrl":"https://i.ytimg.com/vi/PmCVZNqSTYw/mqdefault_live.jpg","startTime":"2024-06-01T06:25:36.0000000\u002B00:00"}]}}