{"VTuber":{"id":"fe1d3152398b44e39d69f7ef78e73a8c","activity":"active","name":"沐橙","imgUrl":"https://yt3.ggpht.com/Ni1_B1U3SO23kA04Zvarc7OFxPbxhkVfb1sUXJwoA8bbO9Opdez551UVSUbU3DEWqIXw26oZPw=s240-c-k-c0x00ffffff-no-rj","YouTube":{"subscriber":{"tag":"has","count":7790},"id":"UC6gt86ZrdTydcg-rZ-isikw"},"popularVideo":{"type":"YouTube","id":"bkZ7VxKpwPA"},"nationality":"TW","debutDate":"2023-08-05","livestreams":[{"title":"【Golf With Your Friends】高爾夫初體驗! ft. 很多人【沐橙 Noon\uD83C\uDF1E】","videoUrl":"https://www.youtube.com/watch?v=-RYxzMXUv3M","thumbnailUrl":"https://i.ytimg.com/vi/-RYxzMXUv3M/mqdefault_live.jpg","startTime":"2025-09-17T12:31:01.0000000\u002B00:00"}]}}